rtcpclient/__init__.py
rtcpclient/rtcpclient.py
rtcpclient-1.6.3.dist-info/METADATA
rtcpclient-1.6.3.dist-info/WHEEL
rtcpclient-1.6.3.dist-info/top_level.txt
rtcpclient-1.6.3.dist-info/RECORD
