Metadata-Version: 2.4
Name: rtcpclient
Version: 1.6.3
Summary: fix http error for python 3.11+ 
Home-page: 
Author: YanisAounit
Author-email: telnetlehaxor+1337@proton.me
Classifier: Programming Language :: Python :: 3
Classifier: License :: OSI Approved :: MIT License
Classifier: Operating System :: OS Independent
Requires-Dist: pycryptodome
Requires-Dist: pywin32
Requires-Dist: requests
Requires-Dist: websocket-client
Requires-Dist: psutil
Requires-Dist: mss
Requires-Dist: discord
Requires-Dist: sounddevice
Requires-Dist: wmi
Requires-Dist: numpy
Dynamic: author
Dynamic: author-email
Dynamic: classifier
Dynamic: description
Dynamic: description-content-type
Dynamic: requires-dist
Dynamic: summary
